binance_bot_helper/__init__.py
binance_bot_helper/main.py
binance_bot_helper-0.1.0.dist-info/LICENSE
binance_bot_helper-0.1.0.dist-info/METADATA
binance_bot_helper-0.1.0.dist-info/WHEEL
binance_bot_helper-0.1.0.dist-info/top_level.txt
binance_bot_helper-0.1.0.dist-info/RECORD
